sphinxcontrib_addmetahtml-0.1.1-py2.7-nspkg.pth
sphinxcontrib/addmetahtml.py
sphinxcontrib_addmetahtml-0.1.1.dist-info/METADATA
sphinxcontrib_addmetahtml-0.1.1.dist-info/RECORD
sphinxcontrib_addmetahtml-0.1.1.dist-info/WHEEL
sphinxcontrib_addmetahtml-0.1.1.dist-info/namespace_packages.txt
sphinxcontrib_addmetahtml-0.1.1.dist-info/top_level.txt
